README.md
setup.py
intellexer/__init__.py
intellexer.egg-info/PKG-INFO
intellexer.egg-info/SOURCES.txt
intellexer.egg-info/dependency_links.txt
intellexer.egg-info/requires.txt
intellexer.egg-info/top_level.txt
intellexer/clusterizer/__init__.py
intellexer/clusterizer/constructors.py
intellexer/clusterizer/interface.py
intellexer/clusterizer/main.py
intellexer/comparator/__init__.py
intellexer/comparator/interface.py
intellexer/comparator/main.py
intellexer/core/__init__.py
intellexer/core/errors.py
intellexer/core/main.py
intellexer/core/request_handler.py
intellexer/core/response_builders.py
intellexer/core/response_wrapper.py
intellexer/core/util.py
intellexer/language_recognizer/__init__.py
intellexer/language_recognizer/interface.py
intellexer/language_recognizer/main.py
intellexer/linguistic_processor/__init__.py
intellexer/linguistic_processor/constructors.py
intellexer/linguistic_processor/interface.py
intellexer/linguistic_processor/main.py
intellexer/multisummarizer/__init__.py
intellexer/multisummarizer/constructors.py
intellexer/multisummarizer/interface.py
intellexer/multisummarizer/main.py
intellexer/named_entity_recognizer/__init__.py
intellexer/named_entity_recognizer/constructors.py
intellexer/named_entity_recognizer/interface.py
intellexer/named_entity_recognizer/main.py
intellexer/natural_language_interface/__init__.py
intellexer/natural_language_interface/interface.py
intellexer/natural_language_interface/main.py
intellexer/preformator/__init__.py
intellexer/preformator/interface.py
intellexer/preformator/main.py
intellexer/sentiment_analyzer/__init__.py
intellexer/sentiment_analyzer/constructors.py
intellexer/sentiment_analyzer/interface.py
intellexer/sentiment_analyzer/main.py
intellexer/spell_checker/__init__.py
intellexer/spell_checker/constructors.py
intellexer/spell_checker/interface.py
intellexer/spell_checker/main.py
intellexer/summarizer/__init__.py
intellexer/summarizer/constructors.py
intellexer/summarizer/interface.py
intellexer/summarizer/main.py
intellexer/topic_modelling/__init__.py
intellexer/topic_modelling/main.py