Metadata-Version: 1.0
Name: intellexer
Version: 1.0
Summary: Intellexer python SDK
Home-page: UNKNOWN
Author: Effective Soft
Author-email: noreplay@example.com
License: UNKNOWN
Platform: UNKNOWN
